autotor/__init__.py
autotor/_metadata.py
autotor/autotor_base.py
autotor/autotor_ip.py
autotor-2.0.0.dist-info/LICENSE
autotor-2.0.0.dist-info/METADATA
autotor-2.0.0.dist-info/WHEEL
autotor-2.0.0.dist-info/top_level.txt
autotor-2.0.0.dist-info/RECORD
