Metadata-Version: 2.1
Name: autotor
Version: 2.0.0
Summary: AutoTor is a simple package to make requests through Tor. It allows automation, easy Tor circuit renewal and customisation of the requests in a threaded way.
Home-page: https://github.com/salvaba94/AutoTor
License: UNKNOWN
Platform: UNKNOWN
Classifier: Programming Language :: Python :: 3
Classifier: License :: OSI Approved :: MIT License
Classifier: Operating System :: Microsoft :: Windows
Requires-Python: >=3.7
License-File: LICENSE
Requires-Dist: requests[socks] (>=2.27.1)
Requires-Dist: stem (>=1.8.0)
Requires-Dist: fake-useragent (>=0.1.11)
